Metadata-Version: 2.3
Name: swarmauri_evaluator_abstractmethods
Version: 0.1.2
Summary: An evaluator that verifies all methods in abstract base classes are properly marked as abstract
License: Apache-2.0
Keywords: abstract methods,code quality,static analysis,evaluator,abstract base class,ABC,interface design,code standards,code evaluation,swarmauri
Author: SwarmAuri Team
Author-email: info@swarmauri.com
Requires-Python: >=3.10,<3.13
Classifier: License :: OSI Approved :: Apache Software License
Classifier: Natural Language :: English
Classifier: Programming Language :: Python :: 3.10
Classifier: Programming Language :: Python :: 3.11
Classifier: Programming Language :: Python :: 3.12
Classifier: Development Status :: 3 - Alpha
Requires-Dist: swarmauri_base
Requires-Dist: swarmauri_core
